[
  {
    "title":"Low Ink",
    "description":"Low ink is a Splatoon tournament that is aimed at newer and lower level competitive teams. Our goal is to give teams a chance to get into the competitive scene and gain experience. High level teams may be barred from playing to preserve our ideology.",
    "imagePath":"images/logo-low-ink.png"
  },
  {
    "title":"SuperJump",
    "description":"The Inkling Performance Labs Major! A tournament for all players and skill levels.",
    "imagePath":"images/SJ.jpg"
  },
  {
    "title":"Swim or Sink",
    "description":"Swim or Sink is a weekly tournament series aimed at providing players with practice against other teams.",
    "imagePath":"images/SwimOrSink_Logo.png"
  },
  {
    "title":"From the Ink Up",
    "description":"From the Ink Up is a ~Division 7-11 skill capped tournament taking place biweekly on Friday evenings.",
    "imagePath":"images/FromTheInkUp_Logo.webp"
  },
  {
    "title":"Splat World Series",
    "description":"Splatoon 3's international supermajor. Presented in collaboration with AREA CUP!",
    "imagePath":"images/SplatWorldSeries_Logo.webp"
  },
  {
    "title":"Global Gauntlet",
    "description":"Splatoon 3's international exchange event. Presented in collaboration with AREA CUP!",
    "imagePath":"images/GlobalGauntlet_Logo.webp"
  }
]
